{"Mode":"gpm_coop","Size":16,"Team":[{"Code":"ru","Name":"Russian Armed Forces","Tickets":300},{"Code":"cf","Name":"Canadian Forces","Tickets":300}],"Assets":[{"Key":"zpu4","InitialDelay":0.0,"RespawnDelay":99999.0,"MaxNrOfSpawns":1,"Team":0,"Position":{"X":-590.626,"Y":25.109,"Z":-89.775},"Rotation":{"X":-47.193,"Y":0.0,"Z":0.0}},{"Key":"fixed_supply_crate_ru","InitialDelay":60.0,"RespawnDelay":30.0,"MaxNrOfSpawns":1,"Team":0,"Position":{"X":-615.144,"Y":25.016,"Z":-62.818},"Rotation":{"X":0.0,"Y":0.0,"Z":0.0}},{"Key":"fixed_supply_crate_ru","InitialDelay":60.0,"RespawnDelay":30.0,"MaxNrOfSpawns":1,"Team":0,"Position":{"X":-543.996,"Y":25.836,"Z":-64.808},"Rotation":{"X":0.0,"Y":0.0,"Z":0.0}},{"Key":"fixed_supply_crate_ru","InitialDelay":60.0,"RespawnDelay":30.0,"MaxNrOfSpawns":1,"Team":0,"Position":{"X":-593.323,"Y":25.199,"Z":-23.433},"Rotation":{"X":0.0,"Y":0.0,"Z":0.0}},{"Key":"fixed_supply_crate_ru","InitialDelay":60.0,"RespawnDelay":30.0,"MaxNrOfSpawns":1,"Team":0,"Position":{"X":-576.761,"Y":26.733,"Z":-61.625},"Rotation":{"X":0.0,"Y":0.0,"Z":0.0}},{"Key":"fixed_supply_crate_ru","InitialDelay":60.0,"RespawnDelay":30.0,"MaxNrOfSpawns":1,"Team":0,"Position":{"X":-1286.573,"Y":26.692,"Z":-464.433},"Rotation":{"X":0.0,"Y":0.0,"Z":0.0}},{"Key":"fixed_supply_crate_ru","InitialDelay":60.0,"RespawnDelay":30.0,"MaxNrOfSpawns":1,"Team":0,"Position":{"X":-1432.846,"Y":25.0,"Z":-543.261},"Rotation":{"X":0.0,"Y":0.0,"Z":0.0}},{"Key":"fixed_supply_crate_ru","InitialDelay":60.0,"RespawnDelay":30.0,"MaxNrOfSpawns":1,"Team":0,"Position":{"X":-1423.549,"Y":25.03,"Z":-504.581},"Rotation":{"X":0.0,"Y":0.0,"Z":0.0}},{"Key":"fixed_supply_crate_ru","InitialDelay":60.0,"RespawnDelay":30.0,"MaxNrOfSpawns":1,"Team":0,"Position":{"X":-1375.276,"Y":25.0,"Z":-549.76},"Rotation":{"X":0.0,"Y":0.0,"Z":0.0}},{"Key":"cf_acv_lav3cpv","InitialDelay":60.0,"RespawnDelay":30.0,"MaxNrOfSpawns":1,"Team":1,"Position":{"X":-1441.68,"Y":25.5,"Z":-523.891},"Rotation":{"X":0.0,"Y":0.0,"Z":0.0}},{"Key":"ru_acv_btr60pu","InitialDelay":60.0,"RespawnDelay":30.0,"MaxNrOfSpawns":1,"Team":0,"Position":{"X":-565.962,"Y":27.137,"Z":-51.997},"Rotation":{"X":0.0,"Y":0.0,"Z":0.0}}],"ControlPoints":[{"Name":"RU Operations 20m","Radius":20,"Team":1,"UnableToChangeTeam":false,"Visible":true,"SupplyGroupId":1,"Position":{"X":-584.781,"Y":21.595,"Z":-52.562}},{"Name":"CF Operations 20m","Radius":20,"Team":2,"UnableToChangeTeam":false,"Visible":true,"SupplyGroupId":4,"Position":{"X":-1290.396,"Y":21.236,"Z":-458.131}},{"Name":"Objective Delta 25m","Radius":25,"Team":0,"UnableToChangeTeam":false,"Visible":true,"SupplyGroupId":2,"Position":{"X":-822.533,"Y":18.459,"Z":-147.652}},{"Name":"Objective Charlie 20m","Radius":20,"Team":0,"UnableToChangeTeam":false,"Visible":true,"SupplyGroupId":3,"Position":{"X":-961.215,"Y":19.47,"Z":-536.666}},{"Name":"Objective Lima 30m","Radius":30,"Team":0,"UnableToChangeTeam":false,"Visible":true,"SupplyGroupId":2,"Position":{"X":-727.269,"Y":19.155,"Z":-375.878}},{"Name":"Objective Kilo 30m","Radius":30,"Team":0,"UnableToChangeTeam":false,"Visible":true,"SupplyGroupId":3,"Position":{"X":-1117.425,"Y":19.845,"Z":-219.118}}],"CombatAreas":[{"Points":[{"X":-487.5232,"Y":-248.0398},{"X":-454.546143,"Y":-113.059082},{"X":-484.096924,"Y":-8.465576},{"X":-546.1273,"Y":55.63867},{"X":-1024.14185,"Y":-110.294189},{"X":-1276.43945,"Y":-232.4718},{"X":-1494.11523,"Y":-414.91272},{"X":-1520.27637,"Y":-522.9492},{"X":-1479.26611,"Y":-620.2987},{"X":-1448.97522,"Y":-701.188354},{"X":-778.6963,"Y":-737.944},{"X":-510.9115,"Y":-426.662476}],"Team":0,"Inverted":false}]}