{"Mode":"gpm_coop","Size":128,"Team":[{"Code":"us","Name":"USMC","Tickets":1000},{"Code":"ch","Name":"Chinese Forces","Tickets":890}],"Assets":[{"Key":"ch_the_z8","InitialDelay":0.0,"RespawnDelay":300.0,"MaxNrOfSpawns":1,"Team":1,"Position":{"X":1992.506,"Y":32.686,"Z":-119.442},"Rotation":{"X":-141.56,"Y":0.0,"Z":0.0}},{"Key":"ch_the_z8","InitialDelay":0.0,"RespawnDelay":300.0,"MaxNrOfSpawns":1,"Team":1,"Position":{"X":2001.059,"Y":35.002,"Z":-76.657},"Rotation":{"X":-141.56,"Y":0.0,"Z":0.0}},{"Key":"fixed_supply_crate_ch","InitialDelay":60.0,"RespawnDelay":30.0,"MaxNrOfSpawns":1,"Team":1,"Position":{"X":1984.75,"Y":32.723,"Z":-151.128},"Rotation":{"X":-170.345,"Y":0.0,"Z":0.0}},{"Key":"fixed_supply_crate_ch","InitialDelay":60.0,"RespawnDelay":30.0,"MaxNrOfSpawns":1,"Team":1,"Position":{"X":1961.817,"Y":16.686,"Z":-258.038},"Rotation":{"X":-169.688,"Y":0.0,"Z":0.0}},{"Key":"ch_ahe_z9wa_hj8","InitialDelay":0.0,"RespawnDelay":600.0,"MaxNrOfSpawns":1,"Team":1,"Position":{"X":1964.736,"Y":33.758,"Z":-251.823},"Rotation":{"X":-141.56,"Y":0.0,"Z":0.0}},{"Key":"ch_ahe_z9wa_hf25","InitialDelay":0.0,"RespawnDelay":600.0,"MaxNrOfSpawns":1,"Team":1,"Position":{"X":1958.729,"Y":33.374,"Z":-284.791},"Rotation":{"X":-141.56,"Y":0.0,"Z":0.0}},{"Key":"ch_ifv_type86","InitialDelay":0.0,"RespawnDelay":300.0,"MaxNrOfSpawns":1,"Team":1,"Position":{"X":1958.215,"Y":14.0,"Z":-279.161},"Rotation":{"X":-169.146,"Y":0.0,"Z":0.0}},{"Key":"ch_ifv_type86","InitialDelay":0.0,"RespawnDelay":300.0,"MaxNrOfSpawns":1,"Team":1,"Position":{"X":1946.367,"Y":14.0,"Z":-276.89},"Rotation":{"X":-169.146,"Y":0.0,"Z":0.0}},{"Key":"boat_rib_agl_mk19","InitialDelay":60.0,"RespawnDelay":30.0,"MaxNrOfSpawns":3,"Team":1,"Position":{"X":1937.531,"Y":14.0,"Z":-300.652},"Rotation":{"X":-168.922,"Y":0.0,"Z":0.0}},{"Key":"boat_rib_agl_mk19","InitialDelay":60.0,"RespawnDelay":30.0,"MaxNrOfSpawns":3,"Team":1,"Position":{"X":1957.596,"Y":14.0,"Z":-304.58},"Rotation":{"X":-168.922,"Y":0.0,"Z":0.0}},{"Key":"vehicle_depot_ch","InitialDelay":0.0,"RespawnDelay":0.0,"MaxNrOfSpawns":1,"Team":1,"Position":{"X":1381.373,"Y":23.813,"Z":-812.837},"Rotation":{"X":-11.928,"Y":0.0,"Z":0.0}},{"Key":"ch_jep_vn3","InitialDelay":0.0,"RespawnDelay":300.0,"MaxNrOfSpawns":1,"Team":1,"Position":{"X":1390.953,"Y":23.723,"Z":-818.765},"Rotation":{"X":-131.883,"Y":0.0,"Z":0.0}},{"Key":"ch_jep_vn3","InitialDelay":0.0,"RespawnDelay":300.0,"MaxNrOfSpawns":1,"Team":1,"Position":{"X":1391.36,"Y":23.726,"Z":-824.695},"Rotation":{"X":-131.883,"Y":0.0,"Z":0.0}},{"Key":"ch_jep_mengshi","InitialDelay":0.0,"RespawnDelay":300.0,"MaxNrOfSpawns":1,"Team":1,"Position":{"X":1391.878,"Y":23.757,"Z":-830.664},"Rotation":{"X":-131.883,"Y":0.0,"Z":0.0}},{"Key":"ch_tnk_ztz99","InitialDelay":0.0,"RespawnDelay":900.0,"MaxNrOfSpawns":1,"Team":1,"Position":{"X":1363.626,"Y":24.133,"Z":-827.991},"Rotation":{"X":128.74,"Y":0.0,"Z":0.0}},{"Key":"ch_trk_logistics","InitialDelay":0.0,"RespawnDelay":300.0,"MaxNrOfSpawns":2,"Team":1,"Position":{"X":1374.95,"Y":23.871,"Z":-816.575},"Rotation":{"X":168.095,"Y":0.0,"Z":0.0}},{"Key":"ch_jep_mengshi","InitialDelay":0.0,"RespawnDelay":300.0,"MaxNrOfSpawns":1,"Team":1,"Position":{"X":1392.502,"Y":23.818,"Z":-836.615},"Rotation":{"X":-131.883,"Y":0.0,"Z":0.0}},{"Key":"ch_jep_mengshi","InitialDelay":0.0,"RespawnDelay":300.0,"MaxNrOfSpawns":1,"Team":1,"Position":{"X":1393.048,"Y":23.84,"Z":-842.342},"Rotation":{"X":-131.883,"Y":0.0,"Z":0.0}},{"Key":"ch_aav_type95","InitialDelay":0.0,"RespawnDelay":600.0,"MaxNrOfSpawns":1,"Team":1,"Position":{"X":1365.299,"Y":23.642,"Z":-836.384},"Rotation":{"X":128.74,"Y":0.0,"Z":0.0}},{"Key":"us_jep_hmmwv_uparmored_alt","InitialDelay":0.0,"RespawnDelay":300.0,"MaxNrOfSpawns":1,"Team":0,"Position":{"X":-1087.08,"Y":22.76,"Z":-501.805},"Rotation":{"X":-120.144,"Y":0.0,"Z":0.0}},{"Key":"us_jep_hmmwv_uparmored_alt","InitialDelay":0.0,"RespawnDelay":300.0,"MaxNrOfSpawns":1,"Team":0,"Position":{"X":-1084.458,"Y":22.76,"Z":-505.21},"Rotation":{"X":-120.144,"Y":0.0,"Z":0.0}},{"Key":"us_jet_a10a_sp","InitialDelay":420.0,"RespawnDelay":600.0,"MaxNrOfSpawns":1,"Team":0,"Position":{"X":-90.664,"Y":22.76,"Z":1153.802},"Rotation":{"X":-122.381,"Y":0.0,"Z":0.0}},{"Key":"us_jet_a10a_sp","InitialDelay":300.0,"RespawnDelay":600.0,"MaxNrOfSpawns":1,"Team":0,"Position":{"X":-114.864,"Y":22.76,"Z":1194.902},"Rotation":{"X":-124.422,"Y":0.0,"Z":0.0}},{"Key":"us_ahe_apache_sp","InitialDelay":900.0,"RespawnDelay":1200.0,"MaxNrOfSpawns":1,"Team":0,"Position":{"X":-1800.029,"Y":188.943,"Z":1874.175},"Rotation":{"X":147.028,"Y":0.0,"Z":0.0}},{"Key":"us_jet_a10a_sp","InitialDelay":540.0,"RespawnDelay":600.0,"MaxNrOfSpawns":1,"Team":0,"Position":{"X":-483.762,"Y":22.76,"Z":918.03},"Rotation":{"X":-121.552,"Y":0.0,"Z":0.0}},{"Key":"us_tnk_m1a1_bf2","InitialDelay":600.0,"RespawnDelay":600.0,"MaxNrOfSpawns":2,"Team":0,"Position":{"X":-312.97,"Y":22.76,"Z":1150.948},"Rotation":{"X":153.96,"Y":0.0,"Z":0.0}},{"Key":"us_tnk_m1a1_bf2","InitialDelay":900.0,"RespawnDelay":600.0,"MaxNrOfSpawns":2,"Team":0,"Position":{"X":-306.735,"Y":22.76,"Z":1155.1},"Rotation":{"X":153.959,"Y":0.0,"Z":0.0}},{"Key":"us_ifv_m2a2_bf2","InitialDelay":600.0,"RespawnDelay":600.0,"MaxNrOfSpawns":2,"Team":0,"Position":{"X":-299.966,"Y":22.76,"Z":1159.588},"Rotation":{"X":157.061,"Y":0.0,"Z":0.0}},{"Key":"us_ifv_m2a2_bf2","InitialDelay":900.0,"RespawnDelay":600.0,"MaxNrOfSpawns":2,"Team":0,"Position":{"X":-294.255,"Y":22.76,"Z":1163.687},"Rotation":{"X":158.579,"Y":0.0,"Z":0.0}},{"Key":"us_tnk_m1a2_alt","InitialDelay":300.0,"RespawnDelay":600.0,"MaxNrOfSpawns":1,"Team":0,"Position":{"X":-723.406,"Y":21.533,"Z":194.935},"Rotation":{"X":-94.261,"Y":0.0,"Z":0.0}},{"Key":"us_ifv_m2a2_bf2","InitialDelay":300.0,"RespawnDelay":600.0,"MaxNrOfSpawns":1,"Team":0,"Position":{"X":-723.025,"Y":21.488,"Z":187.505},"Rotation":{"X":-93.275,"Y":0.0,"Z":0.0}},{"Key":"igla_djigit","InitialDelay":0.0,"RespawnDelay":600.0,"MaxNrOfSpawns":1,"Team":0,"Position":{"X":-701.407,"Y":22.756,"Z":73.097},"Rotation":{"X":161.455,"Y":0.0,"Z":0.0}},{"Key":"igla_djigit","InitialDelay":0.0,"RespawnDelay":600.0,"MaxNrOfSpawns":1,"Team":0,"Position":{"X":-236.282,"Y":21.673,"Z":-524.145},"Rotation":{"X":153.737,"Y":0.0,"Z":0.0}},{"Key":"igla_djigit","InitialDelay":0.0,"RespawnDelay":600.0,"MaxNrOfSpawns":1,"Team":0,"Position":{"X":-224.509,"Y":22.76,"Z":1272.094},"Rotation":{"X":150.51,"Y":0.0,"Z":0.0}},{"Key":"us_tnk_m1a1_bf2","InitialDelay":300.0,"RespawnDelay":600.0,"MaxNrOfSpawns":1,"Team":0,"Position":{"X":-820.887,"Y":48.723,"Z":1063.66},"Rotation":{"X":-170.601,"Y":0.0,"Z":0.0}},{"Key":"us_ifv_m2a2_bf2","InitialDelay":300.0,"RespawnDelay":600.0,"MaxNrOfSpawns":1,"Team":0,"Position":{"X":-815.826,"Y":48.915,"Z":1062.736},"Rotation":{"X":-167.115,"Y":0.0,"Z":0.0}},{"Key":"us_aav_avenger","InitialDelay":600.0,"RespawnDelay":600.0,"MaxNrOfSpawns":1,"Team":0,"Position":{"X":-289.145,"Y":22.76,"Z":1166.729},"Rotation":{"X":160.057,"Y":0.0,"Z":0.0}},{"Key":"us_apc_lav25_bf2","InitialDelay":300.0,"RespawnDelay":600.0,"MaxNrOfSpawns":1,"Team":0,"Position":{"X":-294.642,"Y":21.611,"Z":-344.087},"Rotation":{"X":-96.469,"Y":0.0,"Z":0.0}},{"Key":"us_jep_hmmwv_uparmored_alt","InitialDelay":120.0,"RespawnDelay":300.0,"MaxNrOfSpawns":1,"Team":0,"Position":{"X":-294.717,"Y":21.478,"Z":-338.991},"Rotation":{"X":-96.561,"Y":0.0,"Z":0.0}},{"Key":"us_apc_lav25_bf2","InitialDelay":420.0,"RespawnDelay":600.0,"MaxNrOfSpawns":1,"Team":0,"Position":{"X":-84.701,"Y":26.484,"Z":623.825},"Rotation":{"X":-176.717,"Y":0.0,"Z":0.0}},{"Key":"us_jep_hmmwv_uparmored_alt","InitialDelay":0.0,"RespawnDelay":300.0,"MaxNrOfSpawns":1,"Team":0,"Position":{"X":-85.357,"Y":26.212,"Z":612.865},"Rotation":{"X":-174.488,"Y":0.0,"Z":0.0}},{"Key":"fixed_mortar_ins","InitialDelay":0.0,"RespawnDelay":600.0,"MaxNrOfSpawns":1,"Team":0,"Position":{"X":-404.32,"Y":22.76,"Z":-76.192},"Rotation":{"X":178.07,"Y":0.0,"Z":0.0}},{"Key":"fixed_mortar_ins","InitialDelay":0.0,"RespawnDelay":600.0,"MaxNrOfSpawns":1,"Team":0,"Position":{"X":-1082.38,"Y":22.76,"Z":-496.086},"Rotation":{"X":175.8,"Y":0.0,"Z":0.0}},{"Key":"fixed_mortar_ins","InitialDelay":0.0,"RespawnDelay":600.0,"MaxNrOfSpawns":1,"Team":0,"Position":{"X":-474.122,"Y":22.76,"Z":730.719},"Rotation":{"X":-169.764,"Y":0.0,"Z":0.0}},{"Key":"us_ifv_m2a2_bf2","InitialDelay":1200.0,"RespawnDelay":600.0,"MaxNrOfSpawns":2,"Team":0,"Position":{"X":-293.903,"Y":22.568,"Z":1800.591},"Rotation":{"X":177.555,"Y":0.0,"Z":0.0}},{"Key":"us_tnk_m1a1_alt","InitialDelay":1500.0,"RespawnDelay":600.0,"MaxNrOfSpawns":2,"Team":0,"Position":{"X":-70.369,"Y":22.568,"Z":1793.358},"Rotation":{"X":177.232,"Y":0.0,"Z":0.0}},{"Key":"us_tnk_m1a2_alt","InitialDelay":1500.0,"RespawnDelay":900.0,"MaxNrOfSpawns":2,"Team":0,"Position":{"X":-126.69,"Y":22.568,"Z":1663.003},"Rotation":{"X":176.664,"Y":0.0,"Z":0.0}},{"Key":"aa_m167","InitialDelay":0.0,"RespawnDelay":600.0,"MaxNrOfSpawns":1,"Team":0,"Position":{"X":-385.895,"Y":21.497,"Z":418.572},"Rotation":{"X":0.0,"Y":0.0,"Z":0.0}},{"Key":"aa_m167","InitialDelay":0.0,"RespawnDelay":600.0,"MaxNrOfSpawns":1,"Team":0,"Position":{"X":-390.915,"Y":22.746,"Z":1181.128},"Rotation":{"X":0.0,"Y":0.0,"Z":0.0}},{"Key":"us_ahe_apache_sp","InitialDelay":600.0,"RespawnDelay":600.0,"MaxNrOfSpawns":1,"Team":0,"Position":{"X":-1895.175,"Y":188.3,"Z":1734.788},"Rotation":{"X":147.028,"Y":0.0,"Z":0.0}},{"Key":"us_apc_aavp7a1_bf2","InitialDelay":420.0,"RespawnDelay":600.0,"MaxNrOfSpawns":1,"Team":0,"Position":{"X":-1188.996,"Y":29.123,"Z":249.98},"Rotation":{"X":104.731,"Y":0.0,"Z":0.0}},{"Key":"us_apc_aavp7a1_bf2","InitialDelay":420.0,"RespawnDelay":600.0,"MaxNrOfSpawns":1,"Team":0,"Position":{"X":-1198.115,"Y":28.795,"Z":242.503},"Rotation":{"X":104.731,"Y":0.0,"Z":0.0}},{"Key":"us_aav_avenger","InitialDelay":900.0,"RespawnDelay":600.0,"MaxNrOfSpawns":1,"Team":0,"Position":{"X":-291.749,"Y":22.568,"Z":1735.922},"Rotation":{"X":3.192,"Y":0.0,"Z":0.0}},{"Key":"us_aav_avenger","InitialDelay":900.0,"RespawnDelay":600.0,"MaxNrOfSpawns":1,"Team":0,"Position":{"X":-216.149,"Y":22.568,"Z":1782.525},"Rotation":{"X":176.815,"Y":0.0,"Z":0.0}},{"Key":"ats_tow_ndl","InitialDelay":0.0,"RespawnDelay":900.0,"MaxNrOfSpawns":1,"Team":0,"Position":{"X":-300.076,"Y":21.573,"Z":-311.776},"Rotation":{"X":-95.564,"Y":0.0,"Z":0.0}},{"Key":"ats_tow_ndl","InitialDelay":0.0,"RespawnDelay":900.0,"MaxNrOfSpawns":1,"Team":0,"Position":{"X":-698.826,"Y":36.386,"Z":558.563},"Rotation":{"X":-169.022,"Y":0.0,"Z":0.0}},{"Key":"ch_atm_wz550","InitialDelay":0.0,"RespawnDelay":600.0,"MaxNrOfSpawns":1,"Team":1,"Position":{"X":1366.516,"Y":22.927,"Z":-844.242},"Rotation":{"X":128.74,"Y":0.0,"Z":0.0}},{"Key":"vehicle_depot_ch","InitialDelay":240.0,"RespawnDelay":240.0,"MaxNrOfSpawns":1,"Team":1,"Position":{"X":-1128.692,"Y":22.476,"Z":-1642.762},"Rotation":{"X":98.103,"Y":0.0,"Z":0.0}},{"Key":"us_tnk_m1a2_bf2","InitialDelay":300.0,"RespawnDelay":600.0,"MaxNrOfSpawns":1,"Team":0,"Position":{"X":-381.588,"Y":21.498,"Z":128.816},"Rotation":{"X":180.0,"Y":0.0,"Z":0.0}},{"Key":"us_apc_lav25_bf2","InitialDelay":300.0,"RespawnDelay":600.0,"MaxNrOfSpawns":1,"Team":0,"Position":{"X":-387.869,"Y":21.487,"Z":128.343},"Rotation":{"X":180.0,"Y":0.0,"Z":0.0}},{"Key":"ch_trk_logistics","InitialDelay":240.0,"RespawnDelay":300.0,"MaxNrOfSpawns":2,"Team":1,"Position":{"X":-1131.303,"Y":22.476,"Z":-1635.072},"Rotation":{"X":-83.031,"Y":0.0,"Z":0.0}},{"Key":"us_jet_a10a_sp","InitialDelay":660.0,"RespawnDelay":600.0,"MaxNrOfSpawns":1,"Team":0,"Position":{"X":-503.958,"Y":22.76,"Z":949.854},"Rotation":{"X":-126.358,"Y":0.0,"Z":0.0}},{"Key":"fixed_mortar_ins","InitialDelay":0.0,"RespawnDelay":600.0,"MaxNrOfSpawns":1,"Team":0,"Position":{"X":-570.196,"Y":30.124,"Z":1148.686},"Rotation":{"X":0.0,"Y":0.0,"Z":0.0}},{"Key":"deployable_commandpost_ch","InitialDelay":60.0,"RespawnDelay":30.0,"MaxNrOfSpawns":1,"Team":1,"Position":{"X":1967.653,"Y":32.628,"Z":-239.135},"Rotation":{"X":-169.302,"Y":0.0,"Z":0.0}}],"ControlPoints":[{"Name":"Radar 50m","Radius":50,"Team":0,"UnableToChangeTeam":false,"Visible":true,"SupplyGroupId":8,"Position":{"X":742.892,"Y":104.725,"Z":-1368.073}},{"Name":"CH Type 075","Radius":100,"Team":2,"UnableToChangeTeam":true,"Visible":true,"SupplyGroupId":-1,"Position":{"X":1969.373,"Y":50.961,"Z":-225.012}},{"Name":"Factory 75m","Radius":75,"Team":1,"UnableToChangeTeam":false,"Visible":true,"SupplyGroupId":7,"Position":{"X":-1089.179,"Y":17.017,"Z":-1089.838}},{"Name":"Submarine Pen 100m","Radius":100,"Team":1,"UnableToChangeTeam":false,"Visible":true,"SupplyGroupId":6,"Position":{"X":-480.408,"Y":23.637,"Z":-402.488}},{"Name":"Terminal 70m","Radius":70,"Team":1,"UnableToChangeTeam":false,"Visible":true,"SupplyGroupId":5,"Position":{"X":-686.068,"Y":34.017,"Z":-50.013}},{"Name":"City 70m","Radius":70,"Team":1,"UnableToChangeTeam":false,"Visible":true,"SupplyGroupId":5,"Position":{"X":-270.223,"Y":13.825,"Z":16.624}},{"Name":"Bunker 75m","Radius":75,"Team":1,"UnableToChangeTeam":false,"Visible":true,"SupplyGroupId":4,"Position":{"X":-696.888,"Y":29.165,"Z":195.705}},{"Name":"Airtower 70m","Radius":70,"Team":1,"UnableToChangeTeam":false,"Visible":true,"SupplyGroupId":3,"Position":{"X":-697.757,"Y":32.151,"Z":581.556}},{"Name":"Ghost Town 70m","Radius":70,"Team":1,"UnableToChangeTeam":false,"Visible":true,"SupplyGroupId":3,"Position":{"X":-240.799,"Y":14.28,"Z":466.154}},{"Name":"Hangars 75m","Radius":75,"Team":1,"UnableToChangeTeam":false,"Visible":true,"SupplyGroupId":2,"Position":{"X":-301.92,"Y":16.364,"Z":1205.053}},{"Name":"Barracks 100m","Radius":100,"Team":1,"UnableToChangeTeam":false,"Visible":true,"SupplyGroupId":1,"Position":{"X":-130.631,"Y":14.751,"Z":1710.065}}],"CombatAreas":[{"Points":[{"X":-2048.0,"Y":-2048.0},{"X":2048.0,"Y":-2048.0},{"X":2048.0,"Y":2048.0},{"X":-2048.0,"Y":2048.0}],"Team":0,"Inverted":false}]}